diffsinger_utau/__init__.py
diffsinger_utau/dictionaries/__init__.py
diffsinger_utau/dictionaries/opencpop-extension.txt
diffsinger_utau/samples/00_我多想说再见啊.ds
diffsinger_utau/samples/01_逍遥仙.ds
diffsinger_utau/samples/02_一半一半.ds
diffsinger_utau/samples/03_撒娇八连.ds
diffsinger_utau/samples/04_仙瑶.ds
diffsinger_utau/samples/05_恋人心.ds
diffsinger_utau/samples/06_不谓侠.ds
diffsinger_utau/samples/07_春江花月夜.ds
diffsinger_utau/samples/__init__.py
diffsinger_utau/voice_bank/__init__.py
diffsinger_utau/voice_bank/cli.py
diffsinger_utau/voice_bank/pred_acoustic.py
diffsinger_utau/voice_bank/pred_all.py
diffsinger_utau/voice_bank/pred_duration.py
diffsinger_utau/voice_bank/pred_pitch.py
diffsinger_utau/voice_bank/pred_variance.py
diffsinger_utau/voice_bank/pred_vocoder.py
diffsinger_utau/voice_bank/commons/__init__.py
diffsinger_utau/voice_bank/commons/ds_reader.py
diffsinger_utau/voice_bank/commons/phome_num_counter.py
diffsinger_utau/voice_bank/commons/tts_modules.py
diffsinger_utau/voice_bank/commons/utils.py
diffsinger_utau/voice_bank/commons/variance_input_processor.py
diffsinger_utau/voice_bank/commons/voice_bank_reader.py
diffsinger_utau-0.2.0.dist-info/LICENSE
diffsinger_utau-0.2.0.dist-info/METADATA
diffsinger_utau-0.2.0.dist-info/WHEEL
diffsinger_utau-0.2.0.dist-info/entry_points.txt
diffsinger_utau-0.2.0.dist-info/top_level.txt
diffsinger_utau-0.2.0.dist-info/RECORD
