Metadata-Version: 2.1
Name: diffsinger-utau
Version: 0.2.0
Summary: DiffSinger UTAU inference toolkit with CLI
Author-email: Bingcheng Hu <bingcheng@nyu.edu>
License: MIT
Project-URL: Homepage, https://github.com/bingcheng1998/diffsinger_utau
Project-URL: Repository, https://github.com/bingcheng1998/diffsinger_utau
Project-URL: Issues, https://github.com/bingcheng1998/diffsinger_utau/issues
Classifier: Development Status :: 3 - Alpha
Classifier: Intended Audience :: Developers
Classifier: Intended Audience :: Science/Research
Classifier: License :: OSI Approved :: MIT License
Classifier: Operating System :: OS Independent
Classifier: Programming Language :: Python :: 3
Classifier: Programming Language :: Python :: 3.8
Classifier: Topic :: Multimedia :: Sound/Audio :: Speech
Classifier: Topic :: Scientific/Engineering :: Artificial Intelligence
Requires-Python: <3.9,>=3.8
License-File: LICENSE
Requires-Dist: Setuptools<81
Requires-Dist: numpy<2.0.0
Requires-Dist: librosa<0.10.0
Requires-Dist: PyYAML
Requires-Dist: onnxruntime~=1.16.0
Requires-Dist: torch==1.13.1
Requires-Dist: torchaudio==0.13.1
Requires-Dist: pypinyin
Provides-Extra: dev
Requires-Dist: pytest>=6.0; extra == "dev"
Requires-Dist: black>=22.0; extra == "dev"
Requires-Dist: flake8>=4.0; extra == "dev"
Requires-Dist: mypy>=0.900; extra == "dev"
Provides-Extra: viz
Requires-Dist: matplotlib>=3.5; extra == "viz"
